busGal_api/__init__.py
busGal_api/exceptions.py
busGal_api/known_servers.py
busGal_api/rest_adapter.py
busGal_api/accounts/__init__.py
busGal_api/accounts/accounts.py
busGal_api/accounts/qrutils.py
busGal_api/accounts/xentenovaqr.py
busGal_api/transport/__init__.py
busGal_api/transport/__main__.py
busGal_api/transport/expeditions.py
busGal_api/transport/lines.py
busGal_api/transport/operators.py
busGal_api/transport/rates.py
busGal_api/transport/stops.py
busGal_api/transport/warning_alerts.py
busgal_api-0.3.0.0.dist-info/licenses/LICENSE
busgal_api-0.3.0.0.dist-info/METADATA
busgal_api-0.3.0.0.dist-info/WHEEL
busgal_api-0.3.0.0.dist-info/top_level.txt
busgal_api-0.3.0.0.dist-info/RECORD
