Metadata-Version: 2.4
Name: busGal_api
Version: 0.3.0.0
Summary: Python API wrapper for the galician public transport
Home-page: https://github.com/peprolinbot/bus.gal-api
Author: Pedro Rey Anca
Author-email: contact@peprolinbot.com
Project-URL: Bug Tracker, https://github.com/peprolinbot/bus.gal-api/issues
Project-URL: Documentation, https://peprolinbot.github.io/bus.gal-api
Keywords: bus,buses,transport,public transport,galicia,api
Classifier: Development Status :: 4 - Beta
Classifier: License :: OSI Approved :: GNU General Public License v3 or later (GPLv3+)
Classifier: Programming Language :: Python :: 3
Classifier: Topic :: Software Development :: Libraries :: Python Modules
License-File: LICENSE
Requires-Dist: requests>=2.25.1
Requires-Dist: python-dateutil>=2.9.0.post0
Requires-Dist: pycryptodome>=3.20.0
Requires-Dist: lxml==5.3.0
Dynamic: author
Dynamic: author-email
Dynamic: classifier
Dynamic: description
Dynamic: home-page
Dynamic: keywords
Dynamic: license-file
Dynamic: project-url
Dynamic: requires-dist
Dynamic: summary
